[
  {
    "ContainingType": "WebApiTurnos.Controllers.ServiciosController",
    "Method": "GetAllServicios",
    "RelativePath": "Api/Servicios",
    "HttpMethod": "GET",
    "IsController": true,
    "Order": 0,
    "Parameters": [],
    "ReturnTypes": []
  },
  {
    "ContainingType": "WebApiTurnos.Controllers.ServiciosController",
    "Method": "GetServicio",
    "RelativePath": "Api/Servicios/{id}",
    "HttpMethod": "GET",
    "IsController": true,
    "Order": 0,
    "Parameters": [
      {
        "Name": "id",
        "Type": "System.Int32",
        "IsRequired": true
      }
    ],
    "ReturnTypes": []
  },
  {
    "ContainingType": "WebApiTurnos.Controllers.ServiciosController",
    "Method": "DeleteServicio",
    "RelativePath": "Api/Servicios/{id}",
    "HttpMethod": "DELETE",
    "IsController": true,
    "Order": 0,
    "Parameters": [
      {
        "Name": "id",
        "Type": "System.Int32",
        "IsRequired": true
      }
    ],
    "ReturnTypes": []
  },
  {
    "ContainingType": "WebApiTurnos.Controllers.ServiciosController",
    "Method": "SaveServicio",
    "RelativePath": "Api/Servicios/Servicio",
    "HttpMethod": "POST",
    "IsController": true,
    "Order": 0,
    "Parameters": [
      {
        "Name": "servicio",
        "Type": "WebApiTurnos.Models.TServicio",
        "IsRequired": true
      }
    ],
    "ReturnTypes": []
  },
  {
    "ContainingType": "WebApiTurnos.Controllers.TurnoController",
    "Method": "GetAllTurnos",
    "RelativePath": "Api/Turno",
    "HttpMethod": "GET",
    "IsController": true,
    "Order": 0,
    "Parameters": [],
    "ReturnTypes": []
  },
  {
    "ContainingType": "WebApiTurnos.Controllers.TurnoController",
    "Method": "GetTurno",
    "RelativePath": "Api/Turno/{id}",
    "HttpMethod": "GET",
    "IsController": true,
    "Order": 0,
    "Parameters": [
      {
        "Name": "id",
        "Type": "System.Int32",
        "IsRequired": true
      }
    ],
    "ReturnTypes": []
  },
  {
    "ContainingType": "WebApiTurnos.Controllers.TurnoController",
    "Method": "DeleteTurno",
    "RelativePath": "Api/Turno/{id}",
    "HttpMethod": "DELETE",
    "IsController": true,
    "Order": 0,
    "Parameters": [
      {
        "Name": "id",
        "Type": "System.Int32",
        "IsRequired": true
      }
    ],
    "ReturnTypes": []
  },
  {
    "ContainingType": "WebApiTurnos.Controllers.TurnoController",
    "Method": "SaveTurno",
    "RelativePath": "Api/Turno/Turno",
    "HttpMethod": "POST",
    "IsController": true,
    "Order": 0,
    "Parameters": [
      {
        "Name": "turno",
        "Type": "WebApiTurnos.Models.TTurno",
        "IsRequired": true
      }
    ],
    "ReturnTypes": []
  }
]